inspect2.py
inspect2-0.1.2.dist-info/LICENSE
inspect2-0.1.2.dist-info/METADATA
inspect2-0.1.2.dist-info/WHEEL
inspect2-0.1.2.dist-info/top_level.txt
inspect2-0.1.2.dist-info/RECORD
