Metadata-Version: 2.1
Name: inspect2
Version: 0.1.2
Summary: Backport of the Python 3.6 inspect module to Python 2.7-3.5
Home-page: https://github.com/JelleZijlstra/inspect2
Author: Jelle Zijlstra
Author-email: jelle.zijlstra@gmail.com
License: PSF
Keywords: inspect inspection backport
Platform: UNKNOWN
Classifier: Development Status :: 3 - Alpha
Classifier: Intended Audience :: Developers
Classifier: License :: OSI Approved :: Python Software Foundation License
Classifier: Operating System :: OS Independent
Classifier: Programming Language :: Python :: 2.7
Classifier: Programming Language :: Python :: 3.2
Classifier: Programming Language :: Python :: 3.3
Classifier: Programming Language :: Python :: 3.4
Classifier: Programming Language :: Python :: 3.5
Classifier: Programming Language :: Python :: 3.6
Classifier: Topic :: Software Development
